{
  "Sawai Mansingh Stadium, Jaipur": {
    "batting": {},
    "bowling": {
      "matches": 1,
      "balls": 18,
      "runs": 28,
      "wickets": 0,
      "maidens": 0.3333333333333333,
      "best_bowling": "0/28",
      "overs": 3.0,
      "economy": 9.333333333333334
    }
  },
  "Arun Jaitley Stadium, Delhi": {
    "batting": {},
    "bowling": {
      "matches": 1,
      "balls": 26,
      "runs": 56,
      "wickets": 0,
      "maidens": 0.5,
      "best_bowling": "0/56",
      "overs": 4.333333333333333,
      "economy": 12.923076923076923
    }
  },
  "Bharat Ratna Shri Atal Bihari Vajpayee Ekana Cricket Stadium, Lucknow": {
    "batting": {},
    "bowling": {
      "matches": 1,
      "balls": 26,
      "runs": 30,
      "wickets": 1,
      "maidens": 1.8333333333333333,
      "best_bowling": "1/30",
      "overs": 4.333333333333333,
      "economy": 6.923076923076923,
      "average": 30.0,
      "strike_rate": 26.0
    }
  },
  "Wankhede Stadium, Mumbai": {
    "batting": {},
    "bowling": {
      "matches": 3,
      "balls": 82,
      "runs": 114,
      "wickets": 6,
      "maidens": 4.5,
      "best_bowling": "3/28",
      "overs": 13.666666666666666,
      "economy": 8.341463414634147,
      "average": 19.0,
      "strike_rate": 13.666666666666666
    }
  },
  "Eden Gardens, Kolkata": {
    "batting": {},
    "bowling": {
      "matches": 1,
      "balls": 20,
      "runs": 31,
      "wickets": 1,
      "maidens": 1.0,
      "best_bowling": "1/31",
      "overs": 3.3333333333333335,
      "economy": 9.299999999999999,
      "average": 31.0,
      "strike_rate": 20.0
    }
  }
}