{
  "V Kohli": {
    "batting": {
      "matches": 2,
      "runs": 6,
      "balls": 5,
      "fours": 0,
      "sixes": 0,
      "dots": 0,
      "dismissals": 0,
      "highest": 4,
      "50s": 0,
      "100s": 0,
      "strike_rate": 120.0
    },
    "bowling": {}
  },
  "B Kumar": {
    "batting": {
      "matches": 16,
      "runs": 105,
      "balls": 70,
      "fours": 12,
      "sixes": 4,
      "dots": 29,
      "dismissals": 2,
      "highest": 19,
      "50s": 0,
      "100s": 0,
      "strike_rate": 150.0,
      "average": 52.5
    },
    "bowling": {}
  },
  "SP Narine": {
    "batting": {
      "matches": 9,
      "runs": 37,
      "balls": 47,
      "fours": 1,
      "sixes": 0,
      "dots": 16,
      "dismissals": 1,
      "highest": 11,
      "50s": 0,
      "100s": 0,
      "strike_rate": 78.72340425531915,
      "average": 37.0
    },
    "bowling": {}
  },
  "JD Unadkat": {
    "batting": {
      "matches": 7,
      "runs": 81,
      "balls": 38,
      "fours": 6,
      "sixes": 7,
      "dots": 12,
      "dismissals": 2,
      "highest": 24,
      "50s": 0,
      "100s": 0,
      "strike_rate": 213.1578947368421,
      "average": 40.5
    },
    "bowling": {}
  },
  "Mohammed Shami": {
    "batting": {
      "matches": 10,
      "runs": 106,
      "balls": 62,
      "fours": 14,
      "sixes": 4,
      "dots": 22,
      "dismissals": 2,
      "highest": 24,
      "50s": 0,
      "100s": 0,
      "strike_rate": 170.96774193548387,
      "average": 53.0
    },
    "bowling": {}
  },
  "AR Patel": {
    "batting": {
      "matches": 10,
      "runs": 88,
      "balls": 81,
      "fours": 5,
      "sixes": 4,
      "dots": 31,
      "dismissals": 2,
      "highest": 22,
      "50s": 0,
      "100s": 0,
      "strike_rate": 108.64197530864197,
      "average": 44.0
    },
    "bowling": {}
  },
  "Sandeep Sharma": {
    "batting": {
      "matches": 13,
      "runs": 116,
      "balls": 82,
      "fours": 15,
      "sixes": 3,
      "dots": 28,
      "dismissals": 3,
      "highest": 29,
      "50s": 0,
      "100s": 0,
      "strike_rate": 141.46341463414635,
      "average": 38.666666666666664
    },
    "bowling": {}
  },
  "JJ Bumrah": {
    "batting": {
      "matches": 8,
      "runs": 65,
      "balls": 43,
      "fours": 5,
      "sixes": 4,
      "dots": 16,
      "dismissals": 1,
      "highest": 19,
      "50s": 0,
      "100s": 0,
      "strike_rate": 151.1627906976744,
      "average": 65.0
    },
    "bowling": {}
  },
  "PJ Cummins": {
    "batting": {
      "matches": 6,
      "runs": 71,
      "balls": 43,
      "fours": 6,
      "sixes": 4,
      "dots": 14,
      "dismissals": 2,
      "highest": 27,
      "50s": 0,
      "100s": 0,
      "strike_rate": 165.11627906976744,
      "average": 35.5
    },
    "bowling": {}
  },
  "KV Sharma": {
    "batting": {
      "matches": 2,
      "runs": 7,
      "balls": 6,
      "fours": 0,
      "sixes": 0,
      "dots": 0,
      "dismissals": 0,
      "highest": 6,
      "50s": 0,
      "100s": 0,
      "strike_rate": 116.66666666666667
    },
    "bowling": {}
  },
  "MA Starc": {
    "batting": {
      "matches": 4,
      "runs": 34,
      "balls": 21,
      "fours": 4,
      "sixes": 1,
      "dots": 8,
      "dismissals": 0,
      "highest": 14,
      "50s": 0,
      "100s": 0,
      "strike_rate": 161.9047619047619
    },
    "bowling": {}
  },
  "YS Chahal": {
    "batting": {
      "matches": 12,
      "runs": 44,
      "balls": 50,
      "fours": 1,
      "sixes": 0,
      "dots": 13,
      "dismissals": 3,
      "highest": 6,
      "50s": 0,
      "100s": 0,
      "strike_rate": 88.0,
      "average": 14.666666666666666
    },
    "bowling": {}
  },
  "AD Russell": {
    "batting": {
      "matches": 5,
      "runs": 47,
      "balls": 28,
      "fours": 8,
      "sixes": 0,
      "dots": 7,
      "dismissals": 0,
      "highest": 16,
      "50s": 0,
      "100s": 0,
      "strike_rate": 167.85714285714286
    },
    "bowling": {}
  },
  "TA Boult": {
    "batting": {
      "matches": 14,
      "runs": 109,
      "balls": 98,
      "fours": 16,
      "sixes": 2,
      "dots": 49,
      "dismissals": 4,
      "highest": 20,
      "50s": 0,
      "100s": 0,
      "strike_rate": 111.22448979591837,
      "average": 27.25
    },
    "bowling": {}
  },
  "HV Patel": {
    "batting": {
      "matches": 4,
      "runs": 11,
      "balls": 17,
      "fours": 1,
      "sixes": 0,
      "dots": 9,
      "dismissals": 2,
      "highest": 6,
      "50s": 0,
      "100s": 0,
      "strike_rate": 64.70588235294117,
      "average": 5.5
    },
    "bowling": {}
  },
  "HH Pandya": {
    "batting": {
      "matches": 3,
      "runs": 8,
      "balls": 9,
      "fours": 1,
      "sixes": 0,
      "dots": 4,
      "dismissals": 0,
      "highest": 5,
      "50s": 0,
      "100s": 0,
      "strike_rate": 88.88888888888889
    },
    "bowling": {}
  },
  "J Yadav": {
    "batting": {
      "matches": 1,
      "runs": 3,
      "balls": 3,
      "fours": 0,
      "sixes": 0,
      "dots": 0,
      "dismissals": 0,
      "highest": 3,
      "50s": 0,
      "100s": 0,
      "strike_rate": 100.0
    },
    "bowling": {}
  },
  "GJ Maxwell": {
    "batting": {
      "matches": 3,
      "runs": 6,
      "balls": 6,
      "fours": 1,
      "sixes": 0,
      "dots": 3,
      "dismissals": 1,
      "highest": 5,
      "50s": 0,
      "100s": 0,
      "strike_rate": 100.0,
      "average": 6.0
    },
    "bowling": {}
  },
  "S Gopal": {
    "batting": {
      "matches": 3,
      "runs": 30,
      "balls": 21,
      "fours": 0,
      "sixes": 1,
      "dots": 1,
      "dismissals": 0,
      "highest": 21,
      "50s": 0,
      "100s": 0,
      "strike_rate": 142.85714285714286
    },
    "bowling": {}
  },
  "RA Jadeja": {
    "batting": {
      "matches": 4,
      "runs": 46,
      "balls": 26,
      "fours": 1,
      "sixes": 3,
      "dots": 2,
      "dismissals": 0,
      "highest": 26,
      "50s": 0,
      "100s": 0,
      "strike_rate": 176.92307692307693
    },
    "bowling": {}
  },
  "MM Sharma": {
    "batting": {
      "matches": 3,
      "runs": 32,
      "balls": 17,
      "fours": 6,
      "sixes": 0,
      "dots": 3,
      "dismissals": 1,
      "highest": 18,
      "50s": 0,
      "100s": 0,
      "strike_rate": 188.23529411764707,
      "average": 32.0
    },
    "bowling": {}
  },
  "Rashid Khan": {
    "batting": {
      "matches": 7,
      "runs": 24,
      "balls": 41,
      "fours": 0,
      "sixes": 0,
      "dots": 17,
      "dismissals": 3,
      "highest": 5,
      "50s": 0,
      "100s": 0,
      "strike_rate": 58.53658536585366,
      "average": 8.0
    },
    "bowling": {}
  },
  "Avesh Khan": {
    "batting": {
      "matches": 8,
      "runs": 62,
      "balls": 49,
      "fours": 9,
      "sixes": 0,
      "dots": 17,
      "dismissals": 1,
      "highest": 18,
      "50s": 0,
      "100s": 0,
      "strike_rate": 126.53061224489795,
      "average": 62.0
    },
    "bowling": {}
  },
  "R Tewatia": {
    "batting": {
      "matches": 3,
      "runs": 26,
      "balls": 17,
      "fours": 1,
      "sixes": 2,
      "dots": 4,
      "dismissals": 1,
      "highest": 18,
      "50s": 0,
      "100s": 0,
      "strike_rate": 152.94117647058823,
      "average": 26.0
    },
    "bowling": {}
  },
  "V Shankar": {
    "batting": {
      "matches": 2,
      "runs": 3,
      "balls": 5,
      "fours": 0,
      "sixes": 0,
      "dots": 3,
      "dismissals": 2,
      "highest": 3,
      "50s": 0,
      "100s": 0,
      "strike_rate": 60.0,
      "average": 1.5
    },
    "bowling": {}
  },
  "R Ashwin": {
    "batting": {
      "matches": 9,
      "runs": 72,
      "balls": 68,
      "fours": 4,
      "sixes": 2,
      "dots": 18,
      "dismissals": 1,
      "highest": 12,
      "50s": 0,
      "100s": 0,
      "strike_rate": 105.88235294117646,
      "average": 72.0
    },
    "bowling": {}
  },
  "SM Curran": {
    "batting": {
      "matches": 3,
      "runs": 39,
      "balls": 25,
      "fours": 3,
      "sixes": 2,
      "dots": 7,
      "dismissals": 1,
      "highest": 26,
      "50s": 0,
      "100s": 0,
      "strike_rate": 156.0,
      "average": 39.0
    },
    "bowling": {}
  },
  "M Prasidh Krishna": {
    "batting": {
      "matches": 7,
      "runs": 41,
      "balls": 43,
      "fours": 5,
      "sixes": 0,
      "dots": 23,
      "dismissals": 1,
      "highest": 10,
      "50s": 0,
      "100s": 0,
      "strike_rate": 95.34883720930233,
      "average": 41.0
    },
    "bowling": {}
  },
  "Kuldeep Yadav": {
    "batting": {
      "matches": 2,
      "runs": 18,
      "balls": 20,
      "fours": 1,
      "sixes": 0,
      "dots": 7,
      "dismissals": 0,
      "highest": 12,
      "50s": 0,
      "100s": 0,
      "strike_rate": 90.0
    },
    "bowling": {}
  },
  "KK Ahmed": {
    "batting": {
      "matches": 7,
      "runs": 68,
      "balls": 53,
      "fours": 9,
      "sixes": 2,
      "dots": 27,
      "dismissals": 1,
      "highest": 21,
      "50s": 0,
      "100s": 0,
      "strike_rate": 128.30188679245282,
      "average": 68.0
    },
    "bowling": {}
  },
  "SE Rutherford": {
    "batting": {
      "matches": 1,
      "runs": 10,
      "balls": 7,
      "fours": 0,
      "sixes": 1,
      "dots": 2,
      "dismissals": 0,
      "highest": 10,
      "50s": 0,
      "100s": 0,
      "strike_rate": 142.85714285714286
    },
    "bowling": {}
  },
  "Harpreet Brar": {
    "batting": {
      "matches": 6,
      "runs": 79,
      "balls": 49,
      "fours": 5,
      "sixes": 5,
      "dots": 15,
      "dismissals": 0,
      "highest": 24,
      "50s": 0,
      "100s": 0,
      "strike_rate": 161.22448979591837
    },
    "bowling": {}
  },
  "KH Pandya": {
    "batting": {
      "matches": 7,
      "runs": 69,
      "balls": 57,
      "fours": 6,
      "sixes": 2,
      "dots": 16,
      "dismissals": 1,
      "highest": 17,
      "50s": 0,
      "100s": 0,
      "strike_rate": 121.05263157894737,
      "average": 69.0
    },
    "bowling": {}
  },
  "RD Chahar": {
    "batting": {
      "matches": 5,
      "runs": 54,
      "balls": 46,
      "fours": 3,
      "sixes": 1,
      "dots": 10,
      "dismissals": 1,
      "highest": 16,
      "50s": 0,
      "100s": 0,
      "strike_rate": 117.3913043478261,
      "average": 54.0
    },
    "bowling": {}
  },
  "I Sharma": {
    "batting": {
      "matches": 3,
      "runs": 20,
      "balls": 16,
      "fours": 3,
      "sixes": 0,
      "dots": 5,
      "dismissals": 0,
      "highest": 18,
      "50s": 0,
      "100s": 0,
      "strike_rate": 125.0
    },
    "bowling": {}
  },
  "JC Archer": {
    "batting": {
      "matches": 3,
      "runs": 22,
      "balls": 19,
      "fours": 1,
      "sixes": 1,
      "dots": 8,
      "dismissals": 2,
      "highest": 14,
      "50s": 0,
      "100s": 0,
      "strike_rate": 115.78947368421052,
      "average": 11.0
    },
    "bowling": {}
  },
  "A Nortje": {
    "batting": {
      "matches": 4,
      "runs": 26,
      "balls": 17,
      "fours": 3,
      "sixes": 1,
      "dots": 6,
      "dismissals": 1,
      "highest": 15,
      "50s": 0,
      "100s": 0,
      "strike_rate": 152.94117647058823,
      "average": 26.0
    },
    "bowling": {}
  },
  "K Rabada": {
    "batting": {
      "matches": 3,
      "runs": 16,
      "balls": 15,
      "fours": 3,
      "sixes": 0,
      "dots": 9,
      "dismissals": 3,
      "highest": 9,
      "50s": 0,
      "100s": 0,
      "strike_rate": 106.66666666666667,
      "average": 5.333333333333333
    },
    "bowling": {}
  },
  "T Natarajan": {
    "batting": {
      "matches": 4,
      "runs": 21,
      "balls": 21,
      "fours": 3,
      "sixes": 0,
      "dots": 10,
      "dismissals": 2,
      "highest": 12,
      "50s": 0,
      "100s": 0,
      "strike_rate": 100.0,
      "average": 10.5
    },
    "bowling": {}
  },
  "Ravi Bishnoi": {
    "batting": {
      "matches": 6,
      "runs": 98,
      "balls": 64,
      "fours": 8,
      "sixes": 4,
      "dots": 17,
      "dismissals": 0,
      "highest": 34,
      "50s": 0,
      "100s": 0,
      "strike_rate": 153.125
    },
    "bowling": {}
  },
  "Washington Sundar": {
    "batting": {
      "matches": 3,
      "runs": 8,
      "balls": 8,
      "fours": 0,
      "sixes": 0,
      "dots": 3,
      "dismissals": 1,
      "highest": 5,
      "50s": 0,
      "100s": 0,
      "strike_rate": 100.0,
      "average": 8.0
    },
    "bowling": {}
  },
  "TU Deshpande": {
    "batting": {
      "matches": 4,
      "runs": 47,
      "balls": 31,
      "fours": 6,
      "sixes": 2,
      "dots": 14,
      "dismissals": 0,
      "highest": 21,
      "50s": 0,
      "100s": 0,
      "strike_rate": 151.61290322580646
    },
    "bowling": {}
  },
  "Mohammed Siraj": {
    "batting": {
      "matches": 3,
      "runs": 25,
      "balls": 15,
      "fours": 2,
      "sixes": 2,
      "dots": 6,
      "dismissals": 0,
      "highest": 12,
      "50s": 0,
      "100s": 0,
      "strike_rate": 166.66666666666666
    },
    "bowling": {}
  },
  "Arshdeep Singh": {
    "batting": {
      "matches": 7,
      "runs": 56,
      "balls": 51,
      "fours": 3,
      "sixes": 3,
      "dots": 22,
      "dismissals": 1,
      "highest": 28,
      "50s": 0,
      "100s": 0,
      "strike_rate": 109.80392156862744,
      "average": 56.0
    },
    "bowling": {}
  },
  "C Sakariya": {
    "batting": {
      "matches": 2,
      "runs": 17,
      "balls": 10,
      "fours": 2,
      "sixes": 1,
      "dots": 4,
      "dismissals": 0,
      "highest": 10,
      "50s": 0,
      "100s": 0,
      "strike_rate": 170.0
    },
    "bowling": {}
  },
  "CV Varun": {
    "batting": {
      "matches": 5,
      "runs": 41,
      "balls": 31,
      "fours": 5,
      "sixes": 1,
      "dots": 10,
      "dismissals": 2,
      "highest": 21,
      "50s": 0,
      "100s": 0,
      "strike_rate": 132.25806451612902,
      "average": 20.5
    },
    "bowling": {}
  },
  "KL Nagarkoti": {
    "batting": {
      "matches": 1,
      "runs": 12,
      "balls": 5,
      "fours": 0,
      "sixes": 1,
      "dots": 0,
      "dismissals": 0,
      "highest": 12,
      "50s": 0,
      "100s": 0,
      "strike_rate": 240.0
    },
    "bowling": {}
  },
  "LH Ferguson": {
    "batting": {
      "matches": 3,
      "runs": 58,
      "balls": 29,
      "fours": 8,
      "sixes": 2,
      "dots": 8,
      "dismissals": 0,
      "highest": 40,
      "50s": 0,
      "100s": 0,
      "strike_rate": 200.0
    },
    "bowling": {}
  },
  "Abhishek Sharma": {
    "batting": {
      "matches": 5,
      "runs": 28,
      "balls": 22,
      "fours": 2,
      "sixes": 1,
      "dots": 5,
      "dismissals": 0,
      "highest": 15,
      "50s": 0,
      "100s": 0,
      "strike_rate": 127.27272727272727
    },
    "bowling": {}
  },
  "Akash Singh": {
    "batting": {
      "matches": 2,
      "runs": 20,
      "balls": 9,
      "fours": 2,
      "sixes": 1,
      "dots": 2,
      "dismissals": 0,
      "highest": 17,
      "50s": 0,
      "100s": 0,
      "strike_rate": 222.22222222222223
    },
    "bowling": {}
  },
  "VR Iyer": {
    "batting": {
      "matches": 1,
      "runs": 4,
      "balls": 3,
      "fours": 0,
      "sixes": 0,
      "dots": 0,
      "dismissals": 0,
      "highest": 4,
      "50s": 0,
      "100s": 0,
      "strike_rate": 133.33333333333334
    },
    "bowling": {}
  },
  "LS Livingstone": {
    "batting": {
      "matches": 2,
      "runs": 19,
      "balls": 9,
      "fours": 1,
      "sixes": 1,
      "dots": 1,
      "dismissals": 0,
      "highest": 12,
      "50s": 0,
      "100s": 0,
      "strike_rate": 211.11111111111111
    },
    "bowling": {}
  },
  "MM Ali": {
    "batting": {
      "matches": 3,
      "runs": 7,
      "balls": 7,
      "fours": 0,
      "sixes": 1,
      "dots": 5,
      "dismissals": 2,
      "highest": 6,
      "50s": 0,
      "100s": 0,
      "strike_rate": 100.0,
      "average": 3.5
    },
    "bowling": {}
  },
  "Mukesh Choudhary": {
    "batting": {
      "matches": 2,
      "runs": 30,
      "balls": 14,
      "fours": 3,
      "sixes": 1,
      "dots": 4,
      "dismissals": 0,
      "highest": 24,
      "50s": 0,
      "100s": 0,
      "strike_rate": 214.28571428571428
    },
    "bowling": {}
  },
  "M Theekshana": {
    "batting": {
      "matches": 5,
      "runs": 24,
      "balls": 26,
      "fours": 1,
      "sixes": 1,
      "dots": 10,
      "dismissals": 1,
      "highest": 11,
      "50s": 0,
      "100s": 0,
      "strike_rate": 92.3076923076923,
      "average": 24.0
    },
    "bowling": {}
  },
  "PVD Chameera": {
    "batting": {
      "matches": 1,
      "runs": 7,
      "balls": 5,
      "fours": 1,
      "sixes": 0,
      "dots": 1,
      "dismissals": 0,
      "highest": 7,
      "50s": 0,
      "100s": 0,
      "strike_rate": 140.0
    },
    "bowling": {}
  },
  "MP Stoinis": {
    "batting": {
      "matches": 2,
      "runs": 14,
      "balls": 6,
      "fours": 2,
      "sixes": 0,
      "dots": 0,
      "dismissals": 0,
      "highest": 9,
      "50s": 0,
      "100s": 0,
      "strike_rate": 233.33333333333334
    },
    "bowling": {}
  },
  "M Jansen": {
    "batting": {
      "matches": 1,
      "runs": 0,
      "balls": 2,
      "fours": 0,
      "sixes": 0,
      "dots": 2,
      "dismissals": 1,
      "highest": 0,
      "50s": 0,
      "100s": 0,
      "strike_rate": 0.0,
      "average": 0.0
    },
    "bowling": {}
  },
  "KR Sen": {
    "batting": {
      "matches": 1,
      "runs": 0,
      "balls": 2,
      "fours": 0,
      "sixes": 0,
      "dots": 2,
      "dismissals": 1,
      "highest": 0,
      "50s": 0,
      "100s": 0,
      "strike_rate": 0.0,
      "average": 0.0
    },
    "bowling": {}
  },
  "Simarjeet Singh": {
    "batting": {
      "matches": 1,
      "runs": 8,
      "balls": 5,
      "fours": 1,
      "sixes": 0,
      "dots": 2,
      "dismissals": 0,
      "highest": 8,
      "50s": 0,
      "100s": 0,
      "strike_rate": 160.0
    },
    "bowling": {}
  },
  "Fazalhaq Farooqi": {
    "batting": {
      "matches": 1,
      "runs": 17,
      "balls": 12,
      "fours": 2,
      "sixes": 0,
      "dots": 3,
      "dismissals": 0,
      "highest": 17,
      "50s": 0,
      "100s": 0,
      "strike_rate": 141.66666666666666
    },
    "bowling": {}
  },
  "Umran Malik": {
    "batting": {
      "matches": 1,
      "runs": 16,
      "balls": 5,
      "fours": 2,
      "sixes": 1,
      "dots": 0,
      "dismissals": 0,
      "highest": 16,
      "50s": 0,
      "100s": 0,
      "strike_rate": 320.0
    },
    "bowling": {}
  },
  "Yash Dayal": {
    "batting": {
      "matches": 2,
      "runs": 13,
      "balls": 10,
      "fours": 2,
      "sixes": 0,
      "dots": 3,
      "dismissals": 0,
      "highest": 8,
      "50s": 0,
      "100s": 0,
      "strike_rate": 130.0
    },
    "bowling": {}
  },
  "R Sai Kishore": {
    "batting": {
      "matches": 2,
      "runs": 13,
      "balls": 13,
      "fours": 0,
      "sixes": 0,
      "dots": 3,
      "dismissals": 1,
      "highest": 12,
      "50s": 0,
      "100s": 0,
      "strike_rate": 100.0,
      "average": 13.0
    },
    "bowling": {}
  },
  "Mohsin Khan": {
    "batting": {
      "matches": 1,
      "runs": 0,
      "balls": 1,
      "fours": 0,
      "sixes": 0,
      "dots": 1,
      "dismissals": 1,
      "highest": 0,
      "50s": 0,
      "100s": 0,
      "strike_rate": 0.0,
      "average": 0.0
    },
    "bowling": {}
  },
  "Arshad Khan": {
    "batting": {
      "matches": 1,
      "runs": 0,
      "balls": 2,
      "fours": 0,
      "sixes": 0,
      "dots": 2,
      "dismissals": 1,
      "highest": 0,
      "50s": 0,
      "100s": 0,
      "strike_rate": 0.0,
      "average": 0.0
    },
    "bowling": {}
  },
  "MR Marsh": {
    "batting": {
      "matches": 2,
      "runs": 8,
      "balls": 8,
      "fours": 1,
      "sixes": 0,
      "dots": 3,
      "dismissals": 2,
      "highest": 4,
      "50s": 0,
      "100s": 0,
      "strike_rate": 100.0,
      "average": 4.0
    },
    "bowling": {}
  },
  "M Pathirana": {
    "batting": {
      "matches": 1,
      "runs": 1,
      "balls": 2,
      "fours": 0,
      "sixes": 0,
      "dots": 1,
      "dismissals": 0,
      "highest": 1,
      "50s": 0,
      "100s": 0,
      "strike_rate": 50.0
    },
    "bowling": {}
  },
  "NT Ellis": {
    "batting": {
      "matches": 1,
      "runs": 23,
      "balls": 13,
      "fours": 1,
      "sixes": 2,
      "dots": 4,
      "dismissals": 1,
      "highest": 23,
      "50s": 0,
      "100s": 0,
      "strike_rate": 176.92307692307693,
      "average": 23.0
    },
    "bowling": {}
  },
  "VG Arora": {
    "batting": {
      "matches": 1,
      "runs": 4,
      "balls": 3,
      "fours": 1,
      "sixes": 0,
      "dots": 2,
      "dismissals": 0,
      "highest": 4,
      "50s": 0,
      "100s": 0,
      "strike_rate": 133.33333333333334
    },
    "bowling": {}
  },
  "Suyash Sharma": {
    "batting": {
      "matches": 1,
      "runs": 0,
      "balls": 1,
      "fours": 0,
      "sixes": 0,
      "dots": 1,
      "dismissals": 1,
      "highest": 0,
      "50s": 0,
      "100s": 0,
      "strike_rate": 0.0,
      "average": 0.0
    },
    "bowling": {}
  },
  "Yash Thakur": {
    "batting": {
      "matches": 1,
      "runs": 0,
      "balls": 1,
      "fours": 0,
      "sixes": 0,
      "dots": 1,
      "dismissals": 0,
      "highest": 0,
      "50s": 0,
      "100s": 0,
      "strike_rate": 0.0
    },
    "bowling": {}
  },
  "Mukesh Kumar": {
    "batting": {
      "matches": 2,
      "runs": 13,
      "balls": 8,
      "fours": 3,
      "sixes": 0,
      "dots": 4,
      "dismissals": 1,
      "highest": 13,
      "50s": 0,
      "100s": 0,
      "strike_rate": 162.5,
      "average": 13.0
    },
    "bowling": {}
  },
  "K Kartikeya": {
    "batting": {
      "matches": 1,
      "runs": 7,
      "balls": 7,
      "fours": 0,
      "sixes": 0,
      "dots": 1,
      "dismissals": 0,
      "highest": 7,
      "50s": 0,
      "100s": 0,
      "strike_rate": 100.0
    },
    "bowling": {}
  },
  "A Zampa": {
    "batting": {
      "matches": 1,
      "runs": 14,
      "balls": 11,
      "fours": 1,
      "sixes": 1,
      "dots": 5,
      "dismissals": 0,
      "highest": 14,
      "50s": 0,
      "100s": 0,
      "strike_rate": 127.27272727272727
    },
    "bowling": {}
  },
  "GD Phillips": {
    "batting": {
      "matches": 1,
      "runs": 3,
      "balls": 2,
      "fours": 0,
      "sixes": 0,
      "dots": 0,
      "dismissals": 0,
      "highest": 3,
      "50s": 0,
      "100s": 0,
      "strike_rate": 150.0
    },
    "bowling": {}
  },
  "Noor Ahmad": {
    "batting": {
      "matches": 1,
      "runs": 2,
      "balls": 3,
      "fours": 0,
      "sixes": 0,
      "dots": 1,
      "dismissals": 1,
      "highest": 2,
      "50s": 0,
      "100s": 0,
      "strike_rate": 66.66666666666667,
      "average": 2.0
    },
    "bowling": {}
  },
  "DL Chahar": {
    "batting": {
      "matches": 1,
      "runs": 21,
      "balls": 12,
      "fours": 5,
      "sixes": 0,
      "dots": 6,
      "dismissals": 0,
      "highest": 21,
      "50s": 0,
      "100s": 0,
      "strike_rate": 175.0
    },
    "bowling": {}
  },
  "Harshit Rana": {
    "batting": {
      "matches": 2,
      "runs": 8,
      "balls": 6,
      "fours": 0,
      "sixes": 1,
      "dots": 3,
      "dismissals": 1,
      "highest": 7,
      "50s": 0,
      "100s": 0,
      "strike_rate": 133.33333333333334,
      "average": 8.0
    },
    "bowling": {}
  },
  "M Siddharth": {
    "batting": {
      "matches": 1,
      "runs": 13,
      "balls": 8,
      "fours": 2,
      "sixes": 0,
      "dots": 2,
      "dismissals": 0,
      "highest": 13,
      "50s": 0,
      "100s": 0,
      "strike_rate": 162.5
    },
    "bowling": {}
  },
  "MP Yadav": {
    "batting": {
      "matches": 1,
      "runs": 0,
      "balls": 1,
      "fours": 0,
      "sixes": 0,
      "dots": 1,
      "dismissals": 1,
      "highest": 0,
      "50s": 0,
      "100s": 0,
      "strike_rate": 0.0,
      "average": 0.0
    },
    "bowling": {}
  },
  "R Parag": {
    "batting": {
      "matches": 1,
      "runs": 2,
      "balls": 3,
      "fours": 0,
      "sixes": 0,
      "dots": 1,
      "dismissals": 0,
      "highest": 2,
      "50s": 0,
      "100s": 0,
      "strike_rate": 66.66666666666667
    },
    "bowling": {}
  },
  "G Coetzee": {
    "batting": {
      "matches": 1,
      "runs": 12,
      "balls": 7,
      "fours": 0,
      "sixes": 2,
      "dots": 5,
      "dismissals": 0,
      "highest": 12,
      "50s": 0,
      "100s": 0,
      "strike_rate": 171.42857142857142
    },
    "bowling": {}
  },
  "R Shepherd": {
    "batting": {
      "matches": 1,
      "runs": 12,
      "balls": 6,
      "fours": 2,
      "sixes": 0,
      "dots": 0,
      "dismissals": 0,
      "highest": 12,
      "50s": 0,
      "100s": 0,
      "strike_rate": 200.0
    },
    "bowling": {}
  },
  "Shahbaz Ahmed": {
    "batting": {
      "matches": 1,
      "runs": 17,
      "balls": 5,
      "fours": 1,
      "sixes": 2,
      "dots": 1,
      "dismissals": 0,
      "highest": 17,
      "50s": 0,
      "100s": 0,
      "strike_rate": 340.0
    },
    "bowling": {}
  },
  "M Markande": {
    "batting": {
      "matches": 1,
      "runs": 4,
      "balls": 4,
      "fours": 0,
      "sixes": 0,
      "dots": 0,
      "dismissals": 0,
      "highest": 4,
      "50s": 0,
      "100s": 0,
      "strike_rate": 100.0
    },
    "bowling": {}
  },
  "Azmatullah Omarzai": {
    "batting": {
      "matches": 1,
      "runs": 16,
      "balls": 6,
      "fours": 1,
      "sixes": 2,
      "dots": 3,
      "dismissals": 0,
      "highest": 16,
      "50s": 0,
      "100s": 0,
      "strike_rate": 266.6666666666667
    },
    "bowling": {}
  },
  "MJ Suthar": {
    "batting": {
      "matches": 1,
      "runs": 12,
      "balls": 5,
      "fours": 1,
      "sixes": 1,
      "dots": 1,
      "dismissals": 0,
      "highest": 12,
      "50s": 0,
      "100s": 0,
      "strike_rate": 240.0
    },
    "bowling": {}
  },
  "MJ Santner": {
    "batting": {
      "matches": 1,
      "runs": 8,
      "balls": 9,
      "fours": 0,
      "sixes": 0,
      "dots": 2,
      "dismissals": 0,
      "highest": 8,
      "50s": 0,
      "100s": 0,
      "strike_rate": 88.88888888888889
    },
    "bowling": {}
  }
}